{"items":{"serializeList":[{"name":"hay","nr":17071.0},{"name":"wood","nr":22302.0},{"name":"carrot","nr":285.0},{"name":"pumpkin","nr":2874.0},{"name":"water","nr":266.0},{"name":"fertilizer","nr":47.0},{"name":"power","nr":1311.0673333333364}]},"dockedFiles":[],"minimizedFiles":["actions","farming","main","plot","docs1"],"openFilePositions":[{"key":"actions","value":{"x":1305.1607666015625,"y":511.5194091796875}},{"key":"farming","value":{"x":1328.967529296875,"y":658.058349609375}},{"key":"main","value":{"x":1846.1378173828125,"y":660.773193359375}},{"key":"plot","value":{"x":1301.6171875,"y":584.6173095703125}},{"key":"docs1","value":{"x":1333.9873046875,"y":804.2442626953125}}],"openFileScrollPositions":[{"key":"actions","value":1706.3868408203125},{"key":"farming","value":0.000732421875},{"key":"main","value":831.0518188476563},{"key":"plot","value":-0.000732421875}],"openFileSizes":[{"key":"actions","value":{"x":1841.3134765625,"y":1646.7852783203125}},{"key":"farming","value":{"x":1427.273681640625,"y":1231.9051513671875}},{"key":"main","value":{"x":1787.479736328125,"y":1141.6602783203125}},{"key":"plot","value":{"x":1486.693359375,"y":1040.7940673828125}},{"key":"docs1","value":{"x":900.0,"y":700.0}}],"openDocPages":[{"key":"docs1","value":"docs/output.md"}],"unlocks":["grass_3","soil","harvest","pass","do_a_flip","pet_the_piggy","grassland","hay","straw_hat","carrot_hat","tree_hat","while","true","false","break","continue","loops","speed_5","can_harvest","if","else","elif","expand_5","move","north","south","east","west","for","range","get_world_size","wood","bush","entities","clear","plant","and","or","not","operators","carrots_4","carrot","till","can_trade","trade","items","carrot_seed","trees_2","tree","get_entity_type","get_ground_type","grounds","get_pos_x","get_pos_y","none","num_items","num_unlocked","senses","variables","functions","def","return","global","from","import","traffic_cone","wizard_hat","water","use_item","get_water","watering","pumpkin","pumpkin_seed","dead_pumpkin","pumpkins_4","append","remove","pop","insert","len","list","lists","pumpkin_hat","sunflower_seed","sunflower","power","get_active_power","measure","sunflowers","print","quick_print","unlocks","str","debug","dicts","sets","add","dict","set","dictionaries","min","max","abs","random","utilities","get_companion","polyculture","fertilizer","weird_substance","sunflower_hat"],"version":3}